ianitor/__init__.py
ianitor/args_parser.py
ianitor/script.py
ianitor/service.py
ianitor-0.1.0.dist-info/METADATA
ianitor-0.1.0.dist-info/RECORD
ianitor-0.1.0.dist-info/WHEEL
ianitor-0.1.0.dist-info/entry_points.txt
ianitor-0.1.0.dist-info/top_level.txt
