Metadata-Version: 2.1
Name: ianitor
Version: 0.1.0
Summary: Doorkeeper for consul discovered services.
Home-page: https://github.com/ClearcodeHQ/ianitor
Author: Clearcode - The A Room
Author-email: thearoom@clearcode.cc
License: LGPL
Platform: UNKNOWN
Classifier: Development Status :: 4 - Beta
Classifier: Intended Audience :: Developers
Classifier: Operating System :: OS Independent
Classifier: Programming Language :: Python
Classifier: Programming Language :: Python :: 2
Classifier: Programming Language :: Python :: 2.7
Classifier: Programming Language :: Python :: 3
Classifier: Programming Language :: Python :: 3.3
Classifier: Programming Language :: Python :: 3.4
Classifier: Programming Language :: Python :: 3.5
Classifier: License :: OSI Approved :: GNU Lesser General Public License v3 or later (LGPLv3+)
Requires-Dist: python-consul (<0.8.0,>=0.7.0)
